{
  "name": "Protagonist-Be-Gone!",
  "version": "1.2",
  "links": {
    "homepage": "https://www.gibberlings3.net/forums/topic/36598-protagonist-be-gone-for-bg2-bgt-tutu-bgee-bg2ee-and-eet/"
  },
  "files": [
    {
      "filename": "lin-A7-Protagonist-Be-Gone-v1.2.zip",
      "size": 2669615,
      "download": "https://github.com/Argent77/A7-Protagonist-Be-Gone/releases/download/v1.2/lin-A7-Protagonist-Be-Gone-v1.2.zip",
      "platforms": ["linux"]
    },
    {
      "filename": "mac-A7-Protagonist-Be-Gone-v1.2.zip",
      "size": 2875950,
      "download": "https://github.com/Argent77/A7-Protagonist-Be-Gone/releases/download/v1.2/mac-A7-Protagonist-Be-Gone-v1.2.zip",
      "platforms": ["macos"]
    },
    {
      "filename": "win-A7-Protagonist-Be-Gone-v1.2.zip",
      "size": 2669526,
      "sha256": "a2a31e03dcde9b4ba63eec8bf97ec2959a67a03b5e1a1346dd3949a48e30de4b",
      "download": "https://github.com/Argent77/A7-Protagonist-Be-Gone/releases/download/v1.2/win-A7-Protagonist-Be-Gone-v1.2.zip",
      "platforms": ["windows"]
    }
  ],
  "games": ["bg", "bg2", "bg2ee", "bgee", "bgt", "eet", "sod", "tutu"],
  "categories": ["gameplay"],
  "components": {
    "0": {"type": "std", "category": "spell", "games": ["bgee", "eet", "sod"]},
    "1": {"type": "std", "category": "spell"}
  },
  "languages": {
    "en_US": 0,
    "de_DE": 1,
    "ru_RU": 2,
    "fr_FR": 3
  },
  "translations": {
    "fr_FR": {
      "description": "Ce mod supprime le protagoniste, afin qu'Imoen puisse enfin prendre la place qui lui revient dans le jeu. Pour cette raison, le mod fournit un début \"légèrement\" modifié des parties BG1 et BG2 de la série de jeux. Les extensions du jeu (ToB et SoD) n'ont pas été modifiées.",
      "components": {
        "0": "Protagonist-be-gone pour BG1",
        "1": "Protagonist-be-gone pour BG2"
      }
    },
    "en_US": {
      "description": "This mod removes the protagonist, so that Imoen can finally take his rightful place in the game. For this reason, the mod provides a \"slightly\" modified start to the BG1 and BG2 parts of the game series. The game expansions (ToB and SoD) have not been modified.",
      "components": {
        "0": "Protagonist-be-gone in BG1",
        "1": "Protagonist-be-gone in BG2"
      }
    },
    "zh_CN": {
      "description": "此模组移除了主角，以便爱蒙最终能在游戏中占据她应有的位置。因此，该模组为游戏系列的BG1和BG2部分提供了“略有”修改的开场。游戏扩展（ToB和SoD）未被修改。"
    },
    "de_DE": {
      "components": {
        "0": "Protagonist-ist-fort in BG1",
        "1": "Protagonist-ist-fort in BG2"
      }
    },
    "ru_RU": {
      "components": {
        "0": "Protagonist-be-gone in BG1",
        "1": "Protagonist-be-gone in BG2"
      }
    }
  },
  "tp2": "a7-protagonist-be-gone",
  "safe": 1,
  "authors": ["Argent77"]
}
